{
    "resultcode": "200",
    "reason": "Success",
    "result": {
        "title": "上海市政高校信息",
        "list": [
            {
                "name": "长宁社区学院高教分院",
                "addr": "定西路1300号"
            },
            {
                "name": "东海学院",
                "addr": "虹梅南路6001号"
            },
            {
                "name": "东华大学",
                "addr": "人民北路2999号"
            },
            {
                "name": "东华大学",
                "addr": "延安西路1882号"
            },
            {
                "name": "东华大学科技苑",
                "addr": "新华路365弄6号"
            },
            {
                "name": "东华大学延安路校区",
                "addr": "延安西路延安西路1882号"
            },
            {
                "name": "复旦大学",
                "addr": "邯郸路220号"
            },
            {
                "name": "复旦大学附属医学院",
                "addr": "医学院路138号"
            },
            {
                "name": "复旦大学上海视觉艺术学院",
                "addr": "文翔路2200号"
            },
            {
                "name": "高桥镇文化成年学校",
                "addr": "高桥镇江东路1380弄110号"
            },
            {
                "name": "工程技术大学",
                "addr": "新村路435号"
            },
            {
                "name": "工程技术大学逸仙路校区(住校内从业人员）",
                "addr": "逸仙路58号"
            },
            {
                "name": "虹口区业余大学",
                "addr": "吴淞路297号101室"
            },
            {
                "name": "华东理工大学",
                "addr": "梅陇路130号"
            },
            {
                "name": "华东理工大学网络教育学院杨浦教育中心",
                "addr": "民星路525号-5"
            },
            {
                "name": "华东神学院",
                "addr": "外青松公路7270弄100号"
            },
            {
                "name": "华东师大继续教育学院",
                "addr": "中山北路3663号"
            },
            {
                "name": "华东师范大学",
                "addr": "东川路500号"
            },
            {
                "name": "华东师范大学",
                "addr": "中山北路3663号"
            },
            {
                "name": "华东师范大学",
                "addr": "中山北路中山北路3663号"
            },
            {
                "name": "华东政法大学",
                "addr": "龙源路555号"
            },
            {
                "name": "华东政法学院",
                "addr": "万航渡路1575号107室"
            },
            {
                "name": "黄浦区业余大学",
                "addr": "四川南路37号"
            },
            {
                "name": "加禾商务中心",
                "addr": "中山北路900号"
            },
            {
                "name": "建峰学院",
                "addr": "漠河路1168号"
            },
            {
                "name": "交通大学医学院",
                "addr": "重庆南路227号"
            },
            {
                "name": "交通大学医学院(校外居住)",
                "addr": "重庆南路重庆南路227号"
            },
            {
                "name": "立信会计学校",
                "addr": "中山西路2230号"
            },
            {
                "name": "卢湾区业余大学",
                "addr": "建国西路154号"
            },
            {
                "name": "浦东社区教育学院",
                "addr": "南泉路南泉路1198号"
            },
            {
                "name": "浦东新区电视大学沪东分部",
                "addr": "浦东大道2970弄30号"
            },
            {
                "name": "清华大学经管学院",
                "addr": "虹桥路1591号加23"
            },
            {
                "name": "杉达大学沪东工学院学生宿舍",
                "addr": "沪东新村118号"
            },
            {
                "name": "上海昂立进修学院",
                "addr": "番禺路868号"
            },
            {
                "name": "上海昂立培训中心",
                "addr": "番禺路868号"
            },
            {
                "name": "上海财经大学",
                "addr": "中山北一路369号"
            },
            {
                "name": "上海财经大学(重点部位）国定路校区人文学院实验室",
                "addr": "国定路777号"
            },
            {
                "name": "上海财经大学研究生宿舍",
                "addr": "三门路419号"
            },
            {
                "name": "上海出版印刷高等专科学校",
                "addr": "水丰路100号"
            },
            {
                "name": "上海大学",
                "addr": "嘉定镇城中路20号"
            },
            {
                "name": "上海大学",
                "addr": "延长路149号"
            },
            {
                "name": "上海大学巴士汽车学院",
                "addr": "新场镇下盐路2888号"
            },
            {
                "name": "上海大学成教部",
                "addr": "新闸路1220号 1220号-1---18"
            },
            {
                "name": "上海第二工业大学",
                "addr": "金海路2360号"
            },
            {
                "name": "上海第二工业大学",
                "addr": "陕西北路80号"
            },
            {
                "name": "上海第二医科大学学生公寓",
                "addr": "中山南一路937号"
            },
            {
                "name": "上海电力学院",
                "addr": "惠南镇学海路28号"
            },
            {
                "name": "上海电力学院",
                "addr": "平凉路2103号"
            },
            {
                "name": "上海电视大学",
                "addr": "阜新路25号"
            },
            {
                "name": "上海电视大学",
                "addr": "国顺路288号"
            },
            {
                "name": "上海电视大学黄浦经贸委分校",
                "addr": "南泉北路168号"
            },
            {
                "name": "上海电视大学南汇分校",
                "addr": "惠南镇英雄村136号对面"
            },
            {
                "name": "上海电视大学浦东新区分校",
                "addr": "川沙镇川环南路320号"
            },
            {
                "name": "上海电影艺术职业学院",
                "addr": "达尔文路188号"
            },
            {
                "name": "上海电子信息职业技术学院",
                "addr": "奉城镇洪南路245号"
            },
            {
                "name": "上海对外贸易学院",
                "addr": "古北路620号"
            },
            {
                "name": "上海对外贸易学院",
                "addr": "文翔路1900号"
            },
            {
                "name": "上海对外贸易学院第二食堂",
                "addr": "文汇路308号"
            },
            {
                "name": "上海纺织工业职工大学",
                "addr": "长寿路652号"
            },
            {
                "name": "上海工程技术大学",
                "addr": "龙腾路333号"
            },
            {
                "name": "上海工程技术大学",
                "addr": "仙霞路350号"
            },
            {
                "name": "上海工会管理干部学院",
                "addr": "庄行镇南亭公路2080号"
            },
            {
                "name": "上海工商学院",
                "addr": "华新镇新凤北路565号"
            },
            {
                "name": "上海工艺美术职业学院",
                "addr": "菊园新区嘉行公路851号"
            },
            {
                "name": "上海公安高等专科学校",
                "addr": "凌桥镇崇景路100号"
            },
            {
                "name": "上海海事大学东校区",
                "addr": "浦东大道2632号"
            },
            {
                "name": "上海海事大学民生路校区",
                "addr": "浦东大道1550号"
            },
            {
                "name": "上海海事学院继教部",
                "addr": "乳山路102号-14"
            },
            {
                "name": "上海海洋大学",
                "addr": "沪城环路999号"
            },
            {
                "name": "上海黄浦区业余大学",
                "addr": "东方路408号"
            },
            {
                "name": "上海建桥学院",
                "addr": "康桥镇康桥路1500号"
            },
            {
                "name": "上海建筑工程学校",
                "addr": "龙吴路4989号"
            },
            {
                "name": "上海交通大学",
                "addr": "东川路800号"
            },
            {
                "name": "上海交通大学",
                "addr": "华山路1954号"
            },
            {
                "name": "上海交通大学信息安全学院",
                "addr": "张衡路429号"
            },
            {
                "name": "上海交通大学医学院",
                "addr": "重庆南路280号"
            },
            {
                "name": "上海金融学院",
                "addr": "曹路镇上川路995号"
            },
            {
                "name": "上海科学技术职业学院",
                "addr": "嘉定镇金沙路280号"
            },
            {
                "name": "上海老年大学",
                "addr": "南塘浜路117号"
            },
            {
                "name": "上海理工大学车队",
                "addr": "军工路516号"
            },
            {
                "name": "上海理工大学基础学院",
                "addr": "惠南镇拱极路3800"
            },
            {
                "name": "上海立信会计学院",
                "addr": "文翔路2800号"
            },
            {
                "name": "上海立信会计学院(居住校内）",
                "addr": "中山西路中山西路2230号"
            },
            {
                "name": "上海民办前进进修学院",
                "addr": "瞿溪路801号"
            },
            {
                "name": "上海民远职业技术学院",
                "addr": "唐镇唐陆路3892号"
            },
            {
                "name": "上海欧华职业技术学院",
                "addr": "田林路418号"
            },
            {
                "name": "上海杉达学院",
                "addr": "金海路2727号"
            },
            {
                "name": "上海商学院",
                "addr": "奉浦开发区奉浦大道123号"
            },
            {
                "name": "上海商学院",
                "addr": "中山西路2271号"
            },
            {
                "name": "上海商学院国权路校区",
                "addr": "国权路75号"
            },
            {
                "name": "上海申耀环保实业有限公司",
                "addr": "密云路588号"
            },
            {
                "name": "上海师范大学",
                "addr": "桂林路100号"
            },
            {
                "name": "上海师范大学",
                "addr": "桂林路桂林路100号"
            },
            {
                "name": "上海师范大学天华学院",
                "addr": "胜辛北路1661号"
            },
            {
                "name": "上海市长宁科技进修学院大专部",
                "addr": "桂林路408号"
            },
            {
                "name": "上海市对外经贸进修学院",
                "addr": "江宁路913号"
            },
            {
                "name": "上海市海事职业技术学院",
                "addr": "源深路158号"
            },
            {
                "name": "上海市虹口区社会主义学院",
                "addr": "溧阳路125号"
            },
            {
                "name": "上海市科技管理干部学院",
                "addr": "嘉定镇城中路37号"
            },
            {
                "name": "上海市浦东教育发展研究院",
                "addr": "峨山路180弄13号"
            },
            {
                "name": "上海市普陀区业余大学",
                "addr": "曹杨路805号"
            },
            {
                "name": "上海市轻工职工大学",
                "addr": "漕溪北路502号"
            },
            {
                "name": "上海市行健职业学院",
                "addr": "原平路55号"
            },
            {
                "name": "上海市徐汇区职业培训中心",
                "addr": "中山南二路777弄2号4楼"
            },
            {
                "name": "上海市杨浦区业余大学",
                "addr": "许昌路1461号"
            },
            {
                "name": "上海市住房保障和房屋管理局教育中心上海市房地产学校",
                "addr": "徐泾镇高泾路588号"
            },
            {
                "name": "上海天贤教育后勤服务有限公司",
                "addr": "汇源路777号"
            },
            {
                "name": "上海外国语大学",
                "addr": "文翔路1550号"
            },
            {
                "name": "上海外国语大学贤达经济人文学院",
                "addr": "东体育会路390号"
            },
            {
                "name": "上海物资集团教育培训中心",
                "addr": "龙华路1831号"
            },
            {
                "name": "上海戏剧学院",
                "addr": "华山路630号"
            },
            {
                "name": "上海戏剧学院分院",
                "addr": "莲花路211号"
            },
            {
                "name": "上海行知学院",
                "addr": "永乐路737号"
            },
            {
                "name": "上海杨浦区老年大学",
                "addr": "贵阳路143弄86号"
            },
            {
                "name": "上海医疗器械专科学校",
                "addr": "同济支路199号"
            },
            {
                "name": "上海医药高等专科学校",
                "addr": "周浦镇周祝公路279号"
            },
            {
                "name": "上海应用技术学院",
                "addr": "漕宝路120号"
            },
            {
                "name": "上海应用技术学院",
                "addr": "漕宝路121号"
            },
            {
                "name": "上海震旦职业学院",
                "addr": "市一路88号"
            },
            {
                "name": "上海政法学院",
                "addr": "外青松公路7989号"
            },
            {
                "name": "上海中博专修学院",
                "addr": "金山卫镇学府路1300号"
            },
            {
                "name": "上海中医药大学",
                "addr": "蔡伦路1200号"
            },
            {
                "name": "市委宣传党校",
                "addr": "梅陇四村95号三楼"
            },
            {
                "name": "同济大学",
                "addr": "曹安路4800号"
            },
            {
                "name": "同济大学",
                "addr": "四平路1239号"
            },
            {
                "name": "同济大学沪西校区",
                "addr": "真南路500号"
            },
            {
                "name": "同济大学同科学院",
                "addr": "共和新路1238号"
            },
            {
                "name": "徐汇区业余大学",
                "addr": "大木桥路434号"
            },
            {
                "name": "杨浦区·业余大学",
                "addr": "许昌路1461号"
            },
            {
                "name": "杨浦区委党校",
                "addr": "平凉路2691号"
            },
            {
                "name": "应用技术学院建筑设计院",
                "addr": "漕宝路121号"
            },
            {
                "name": "中共上海市农场管理局委员会党校",
                "addr": "天山西路231号"
            },
            {
                "name": "中国美术学院上海设计学院",
                "addr": "张江镇春晓路109号"
            },
            {
                "name": "中欧国际工商学院",
                "addr": "红枫路699号"
            },
            {
                "name": "中医学院",
                "addr": "零陵路530号"
            }
        ]
    },
    "error_code": 0
}